Metadata-Version: 2.4
Name: scd-polars-matching-plugin
Version: 0.1.0
Classifier: Development Status :: 4 - Beta
Classifier: Intended Audience :: Science/Research
Classifier: License :: OSI Approved :: MIT License
Classifier: Programming Language :: Python :: 3
Classifier: Programming Language :: Python :: 3.11
Classifier: Programming Language :: Python :: 3.12
Classifier: Programming Language :: Python :: 3.13
Classifier: Programming Language :: Rust
Classifier: Programming Language :: Python :: Implementation :: CPython
Classifier: Programming Language :: Python :: Implementation :: PyPy
Classifier: Topic :: Scientific/Engineering :: Medical Science Apps.
Classifier: Topic :: Scientific/Engineering :: Information Analysis
License-File: LICENSE
Summary: High-performance Rust-based plugin for Polars that performs epidemiologically sound case-control matching with proper risk-set sampling methodology
Keywords: epidemiology,case-control,matching,polars,rust,scd
Author: Tobias Kragholm
License: MIT
Requires-Python: >=3.11
